Exemplo-TPFinal/decodificador.v
module decodificador(in, out);
input [2:0] in;
output [7:0] out;

reg [7:0] out;

always @(in) begin
	case(in)
			3'b000:begin
			 	out <= 8'b10000000;
			end
			3'b001:begin
			 	out <= 8'b01000000;
			end
			3'b010:begin
			 	out <= 8'b00100000;
			end
			3'b011:begin
			 	out <= 8'b00010000;
			end
			3'b100:begin
			 	out <= 8'b00001000;
			end
			3'b101:begin
			 	out <= 8'b00000100;
			end
			3'b110:begin 
				out <= 8'b00000010;
			end
			3'b111:begin 
				out <= 8'b00000001;
			end
	endcase
end
endmodule

Exemplo/teste.v
`include "decodificador.v"
module teste;
reg [2:0] inn;
wire [7:0] out;
decodificador d(inn, out);

initial $dumpfile("teste.vcd");
initial $dumpvars(0, teste);


initial begin
	# 1 inn = 3'b000;
	# 1 inn = 3'b001;
	# 1 inn = 3'b010;
	# 1 inn = 3'b011;
	# 1 inn = 3'b100;
	# 1 inn = 3'b101;
	# 1 inn = 3'b110;
	# 1 inn = 3'b111;
	# 20 $finish;
end

endmodule

Exemplo/teste.vcd
$date
	Thu Jun 11 23:13:08 2015
$end
$version
	Icarus Verilog
$end
$timescale
	1s
$end
$scope module teste $end
$var wire 8 ! out [7:0] $end
$var reg 3 " inn [2:0] $end
$scope module d $end
$var wire 3 # in [2:0] $end
$var reg 8 $ out [7:0] $end
$upscope $end
$upscope $end
$enddefinitions $end
#0
$dumpvars
bx $
bx #
bx "
bx !
$end
#1
b10000000 $
b10000000 !
b0 "
b0 #
#2
b1000000 $
b1000000 !
b1 "
b1 #
#3
b100000 $
b100000 !
b10 "
b10 #
#4
b10000 $
b10000 !
b11 "
b11 #
#5
b1000 $
b1000 !
b100 "
b100 #
#6
b100 $
b100 !
b101 "
b101 #
#7
b10 $
b10 !
b110 "
b110 #
#8
b1 $
b1 !
b111 "
b111 #
