TP0/register_bank/bank.v
module bank (clock, clear, dataReadA, dataReadB, readRegA, readRegB, writeReg, readWrite, writeData); // Falta passar o register para o module pelo testbench

	input clock, clear;
	input [4:0] readRegA, readRegB, writeReg;
	input readWrite;
	input [31:0] writeData;
	reg [31:0] register[31:0];
	output reg [31:0] dataReadA, dataReadB;

	always @ (posedge clock)
	begin
		/* Declaracao dos registradores e seus respectivos valores hipoteticos */
		register[0] = 0*2;
		register[1] = 1*2;
		register[2] = 2*2;
		register[3] = 3*2;
		register[4] = 4*2;
		register[5] = 5*2;
		register[6] = 6*2;
		register[7] = 7*2;
		register[8] = 8*2;
		register[9] = 9*2;
		register[10] = 10*2;
		register[11] = 11*2;
		register[12] = 12*2;
		register[13] = 13*2;
		register[14] = 14*2;
		register[15] = 15*2;
		register[16] = 16*2;
		register[17] = 17*2;
		register[18] = 18*2;
		register[19] = 19*2;
		register[20] = 20*2;
		register[21] = 21*2;
		register[22] = 22*2;
		register[23] = 23*2;
		register[24] = 24*2;
		register[25] = 25*2;
		register[26] = 26*2;
		register[27] = 27*2;
		register[28] = 28*2;
		register[29] = 29*2;
		register[30] = 30*2;
		register[31] = 31*2;

		dataReadA = register[readRegA];
		dataReadB = register[readRegB];

		if (readWrite == 1)
			register[writeReg] = writeData;

		if (clear == 1)
		begin
			dataReadA = 0;
			dataReadB = 0;
		end
	end
endmodule // bank

TP0/register_bank/testbench.v
`include "bank.v"

module testbench;

	reg clock = 0, clear = 0;
	reg [4:0] readRegA, readRegB, writeReg;
	reg readWrite;
	reg [31:0] writeData;
	wire [31:0] dataReadA, dataReadB;

	always #1 clock = !clock;

	initial $dumpfile("testbench.vcd");
	initial $dumpvars(0, testbench);

	bank c(clock, clear, dataReadA, dataReadB, readRegA, readRegB, writeReg, readWrite, writeData);

	initial
	begin
		#1 clear = 1;
		#1 clear = 0;
		#1 readRegA = 4;
		#1 readRegB = 7;
		#1 readWrite = 1;
		#0 writeData = 22;
		#0 writeReg = 20;
		#1 readWrite = 0;
		#5 clear = 1;
		#5 $finish;
	end

endmodule // testbench

TP0/register_bank/testbench.vcd
$date
	Sat Jul  2 14:29:34 2016
$end
$version
	Icarus Verilog
$end
$timescale
	1s
$end
$scope module testbench $end
$var wire 32 ! dataReadA [31:0] $end
$var wire 32 " dataReadB [31:0] $end
$var reg 1 # clear $end
$var reg 1 $ clock $end
$var reg 5 % readRegA [4:0] $end
$var reg 5 & readRegB [4:0] $end
$var reg 1 ' readWrite $end
$var reg 32 ( writeData [31:0] $end
$var reg 5 ) writeReg [4:0] $end
$scope module c $end
$var wire 1 * clear $end
$var wire 1 + clock $end
$var wire 5 , readRegA [4:0] $end
$var wire 5 - readRegB [4:0] $end
$var wire 1 . readWrite $end
$var wire 32 / writeData [31:0] $end
$var wire 5 0 writeReg [4:0] $end
$var reg 32 1 dataReadA [31:0] $end
$var reg 32 2 dataReadB [31:0] $end
$upscope $end
$upscope $end
$enddefinitions $end
#0
$dumpvars
bx 2
bx 1
bx 0
bx /
x.
bx -
bx ,
0+
0*
bx )
bx (
x'
bx &
bx %
0$
0#
bx "
bx !
$end
#1
b0 2
b0 "
b0 1
b0 !
1#
1*
1$
1+
#2
0#
0*
0$
0+
#3
bx 2
bx "
b1000 1
b1000 !
b100 %
b100 ,
1$
1+
#4
b111 &
b111 -
0$
0+
#5
b10100 )
b10100 0
b10110 (
b10110 /
b1110 2
b1110 "
1'
1.
1$
1+
#6
0'
0.
0$
0+
#7
1$
1+
#8
0$
0+
#9
1$
1+
#10
0$
0+
#11
b0 2
b0 "
b0 1
b0 !
1$
1+
1#
1*
#12
0$
0+
#13
b0 2
b0 "
b0 1
b0 !
1$
1+
#14
0$
0+
#15
b0 2
b0 "
b0 1
b0 !
1$
1+
