TPFinal - Quartus II/register_bank/register_bank.v
module register_bank(in, enable, clock, out);

	input enable, clock;
	input [15:0] in;
	output reg [15:0] out;

	always @ (posedge clock)
	begin
		if(enable)
		begin
			out <= in;
		end
	end

endmodule

TPFinal/alu/alu.v
module alu(a, b, OpSelect, result);

	input [15:0] a, b;
	input OpSelect;
	output reg [15:0] result;

	always @ ( * )
	begin
		case (OpSelect)
			1'b1: result = a + b;
			1'b0: result = a ~& b;
			default: result = 0;
		endcase
	end

endmodule

TPFinal/multiplexer/multiplexer.v
module multiplexer(imediate,  r0, r1, r2, r3, r4, r5, r6, r7, r, imediate_select,  r0_select, r1_select, r2_select, r3_select, r4_select, r5_select, r6_select, r7_select, r_select,bus);

	input [15:0] imediate, r0, r1, r2, r3, r4, r5, r6, r7, r;
	input imediate_select, r0_select, r1_select, r2_select, r3_select, r4_select, r5_select, r6_select, r7_select, r_select;
	output [15:0] bus;
	reg [15:0] bus;

	always @(imediate_select or r0_select or r1_select or r2_select or r3_select or r4_select or r5_select or r6_select or r7_select or r_select)
	begin
			if(imediate_select == 1)
		 		bus <= imediate;

		 	else if(r_select == 1)
		 		bus <= r;

		 	else if(r0_select == 1)
		 		bus <= r0;

		 	else if(r1_select == 1)
		 		bus <= r1;

		 	else if(r2_select == 1)
		 		bus <= r2;

		 	else if(r3_select == 1)
		 		bus <= r3;

		 	else if(r4_select == 1)
		 		bus <= r4;

		 	else if(r5_select == 1)
		 		bus <= r5;

		 	else if(r6_select == 1)
		 		bus <= r6;

		 	else if(r7_select == 1)
		 		bus <= r7;

		 	else
				bus <= 16'b0000000000000000;
	end

endmodule

TPFinal/decoder.v
module decoder (out, register);

	input [2:0] register;
	output reg [7:0] out;

	always @ (register)
	begin
		case(register)
			3'b000: out <= 8'b10000000; // r7
			3'b001: out <= 8'b01000000; // r6
			3'b010:	out <= 8'b00100000; // r5
			3'b011:	out <= 8'b00010000; // r4
			3'b100:	out <= 8'b00001000; // r3
			3'b101:	out <= 8'b00000100; // r2
			3'b110:	out <= 8'b00000010; // r1
			3'b111:	out <= 8'b00000001; // r0
		endcase
	end

endmodule

TPFinal/control_unit/control_unit.v
module control_unit(in, resetn, count, r0_select, r1_select, r2_select, r3_select, r4_select, r5_select, r6_select, r7_select, r_select, immediate_select, r0_enable, r1_enable, r2_enable, r3_enable, r4_enable, r5_enable, r6_enable, r7_enable, a_enable, r_enable, opSelect, clear, negativo);

	input [8:0] in;
	input [1:0] count;
	input resetn;
	output reg r0_select, r1_select, r2_select, r3_select, r4_select, r5_select, r6_select, r7_select, r_select, immediate_select;
	output reg r0_enable, r1_enable, r2_enable, r3_enable, r4_enable, r5_enable, r6_enable, r7_enable, a_enable, r_enable, clear;
	output reg opSelect, negativo;
	reg [2:0] operation;
	reg [2:0] registera, registerb;
	reg [1:0] status;
	reg saida, negar;
	wire [7:0] outRegistera, outRegisterb, outEnableRegister;

	decoder dec_1(registera, outRegistera);
	decoder dec_2(registerb, outRegisterb);
	decoder dec_3(registera, outEnableRegister);

	always @(posedge resetn) begin
		if(resetn == 1)
			clear <= 1;
		else
			clear <= 0;
	end

	always @(in or count) begin
		operation = {in[8], in[7], in[6]};
		registera = {in[5], in[4], in[3]};
		registerb = {in[2], in[1], in[0]};
		clear <= 0;
		case (count)
				2'b00:begin // Primeiro Ciclo
					r_select <= 0;
					r0_enable <= 0;
					r1_enable <= 0;
					r2_enable <= 0;
					r3_enable <= 0;
					r4_enable <= 0;
					r5_enable <= 0;
					r6_enable <= 0;
					r7_enable <= 0;
					if(operation == 3'b111) begin
							opSelect <= 1; //REP
							status <= 2'b01;
							negar <= 0;
							saida <= 0;
					end
					else if(operation == 3'b101) begin
							opSelect <= 1; //LDI
							status <= 2'b11;
							negar <= 0;
							saida <= 0;
					end
					else if(operation == 3'b000) begin
						opSelect <= 1;// SUM
						status <= 2'b00;
						negar <= 0;
						saida <= 0;
					end
					else if(operation == 3'b001) begin
							opSelect <= 1;// SUB
							status <= 2'b00;
							negar <= 1;
							saida <= 0;
					end
					else if(operation == 3'b010) begin
							opSelect <= 0; //NAN
							status <= 2'b00;
							negar <= 0;
							saida <= 0;
					end
					else if(operation == 3'b100) begin
							opSelect <= 1; //OUT
							status <= 2'b01;
							negar <= 0;
							saida <= 1;
					end

				end
				2'b01:begin// Segundo Ciclo
					a_enable <= 1;
					if(status == 2'b00 || status == 2'b10 && saida == 1) begin
						immediate_select <= 0;
						r_select <= 0;
						r0_select <= outRegistera[7];
						r1_select <= outRegistera[6];
						r2_select <= outRegistera[5];
						r3_select <= outRegistera[4];
						r4_select <= outRegistera[3];
						r5_select <= outRegistera[2];
						r6_select <= outRegistera[1];
						r7_select <= outRegistera[0];
					end else if(status == 2'b01 || 2'b11) begin
						immediate_select <= 0;
						r_select <= 0;
						r0_select <= 0;
						r1_select <= 0;
						r2_select <= 0;
						r3_select <= 0;
						r4_select <= 0;
						r5_select <= 0;
						r6_select <= 0;
						r7_select <= 0;
					end
				end
				2'b10:begin// Terceiro Ciclo
					a_enable <= 0;
					r_enable <= 1;
					if(status != 2'b11) begin
						immediate_select <= 0;
						r_select <= 0;
						r0_select <= outRegisterb[7];
						r1_select <= outRegisterb[6];
						r2_select <= outRegisterb[5];
						r3_select <= outRegisterb[4];
						r4_select <= outRegisterb[3];
						r5_select <= outRegisterb[2];
						r6_select <= outRegisterb[1];
						r7_select <= outRegisterb[0];
					end
					else begin
						immediate_select <= 1;
						r_select <= 0;
					end

					if(negar == 1)begin
						negativo <= 1;
					end
				end
				2'b11:begin// Quarto Ciclo
					negativo <= 0;
					r_enable <= 0;
					immediate_select <= 0;
					r_select <= 1;
					status = 2'bxx;
					r0_enable = outEnableRegister[7];
					r1_enable = outEnableRegister[6];
					r2_enable = outEnableRegister[5];
					r3_enable = outEnableRegister[4];
					r4_enable = outEnableRegister[3];
					r5_enable = outEnableRegister[2];
					r6_enable = outEnableRegister[1];
					r7_enable = outEnableRegister[0];
				end
			endcase
	end
	endmodule

counter.v
module counter(clock, clear, out);

	input clock, clear;
	output reg [1:0] out;

	always @ (posedge clock)
	begin
		if(clear == 0)
			out = out + 1'b1;
		else
			out = 2'b00;
	end

endmodule

TPFinal/extensor/extensor.v
module extensor(iin, out);

	input [15:0] iin;
	output reg [15:0] out;
	reg [9:0] imediate;

	always @ (iin)
	begin
		imediate = {iin[9], iin[8], iin[7], iin[6], iin[5], iin[4], iin[3], iin[2], iin[1], iin[0]};

		out <= {6'b000000, imediate};
	end

endmodule

TPFinal/complement/complement.v
module complement(iin, enable, out);

input [15:0] iin;
input enable;
output reg [15:0] out;

always @(iin or enable)
begin
	if(enable == 1)
		out <= - iin;
	else
		out <= iin;
end

endmodule

TPFinal/processor.v
`include "./complement/complement.v"
`include "./register_bank/register_bank.v"
`include "./alu/alu.v"
`include "./extensor/extensor.v"
`include "./counter/counter.v"
`include "./multiplexer/multiplexer.v"
`include "./decoder/decoder.v"
`include "./control_unit/control_unit.v"

module processor(clock, iin, resetn, outputProcessor);

	input [15:0] iin;
	input clock, resetn;
	output reg [15:0] outputProcessor;
	wire [1:0] cont;
	wire [15:0] imediate;
	wire r0_select, r1_select, r2_select, r3_select, r4_select, r5_select, r6_select, r7_select, r_select, immediate_select;
	wire r0_enable, r1_enable, r2_enable, r3_enable, r4_enable, r5_enable, r6_enable, r7_enable, a_enable, r_enable;
	wire OperationSelect, clear, negativo;
	wire [15:0] saida, bus, out;
	wire [15:0] r0, r1, r2, r3, r4, r5, r6, r7, r, a;
	reg [8:0] in;

	always @ (bus)
	begin
		outputProcessor <= bus;
	end

	always @ (iin)
	begin
		in <= iin[15:7];
	end

	complement comp(saida, negativo, bus);

	extensor ext(iin, imediate);

	counter count(clock, resetn, cont);

	control_unit ctrl(in, resetn, cont, r0_select, r1_select, r2_select, r3_select, r4_select, r5_select, r6_select, r7_select, r_select, immediate_select, r0_enable, r1_enable, r2_enable, r3_enable, r4_enable, r5_enable, r6_enable, r7_enable, a_enable, r_enable, OperationSelect, clear, negativo);

	multiplexer mux(saida, imediate, imediate_select, r, r_select, r0, r0_select, r1, r1_select, r2, r2_select, r3, r3_select, r4, r4_select, r5, r5_select, r6, r6_select, r7, r7_select);

	alu alu(a, bus, OperationSelect, out);
	register_bank R0(bus, r0_enable, clock, r0);
	register_bank R1(bus, r1_enable, clock, r1);
	register_bank R2(bus, r2_enable, clock, r2);
	register_bank R3(bus, r3_enable, clock, r3);
	register_bank R4(bus, r4_enable, clock, r4);
	register_bank R5(bus, r5_enable, clock, r5);
	register_bank R6(bus, r6_enable, clock, r6);
	register_bank R7(bus, r7_enable, clock, r7);
	register_bank Rr(bus, r_enable, clock, r);
	register_bank Ra(bus, a_enable, clock, a);

endmodule

TPFinal/testbench.v
`include "processor.v"

module testbench;
	reg clock = 0;
	reg [15:0] iin;
	reg resetn = 1;

	wire [15:0] bus;

	always #1 clock = !clock;

	initial $dumpfile("testbench.vcd");
	initial $dumpvars(0, testbench);

	processor p(clock, iin, resetn, bus);

	initial begin
		#0 resetn = 1'b0;
		#8 iin = 16'b1010000000011100;
		#8 iin = 16'b1010010000001010;
		#8 iin = 16'b0010000010000000;
		#8 iin = 16'b1000000000000000;
		#8 $finish;
	end
endmodule

TPFinal/testbench.vcd
$date
	Mon Jul  4 01:30:38 2016
$end
$version
	Icarus Verilog
$end
$timescale
	1s
$end
$scope module testbench $end
$var wire 16 ! bus [15:0] $end
$var reg 1 " clock $end
$var reg 16 # iin [15:0] $end
$var reg 1 $ resetn $end
$scope module p $end
$var wire 1 % OperationSelect $end
$var wire 16 & a [15:0] $end
$var wire 1 ' a_enable $end
$var wire 16 ( bus [15:0] $end
$var wire 1 ) clear $end
$var wire 1 * clock $end
$var wire 2 + cont [1:0] $end
$var wire 16 , iin [15:0] $end
$var wire 16 - imediate [15:0] $end
$var wire 1 . imediate_select $end
$var wire 1 / immediate_select $end
$var wire 1 0 negativo $end
$var wire 16 1 out [15:0] $end
$var wire 16 2 r [15:0] $end
$var wire 16 3 r0 [15:0] $end
$var wire 1 4 r0_enable $end
$var wire 1 5 r0_select $end
$var wire 16 6 r1 [15:0] $end
$var wire 1 7 r1_enable $end
$var wire 1 8 r1_select $end
$var wire 16 9 r2 [15:0] $end
$var wire 1 : r2_enable $end
$var wire 1 ; r2_select $end
$var wire 16 < r3 [15:0] $end
$var wire 1 = r3_enable $end
$var wire 1 > r3_select $end
$var wire 16 ? r4 [15:0] $end
$var wire 1 @ r4_enable $end
$var wire 1 A r4_select $end
$var wire 16 B r5 [15:0] $end
$var wire 1 C r5_enable $end
$var wire 1 D r5_select $end
$var wire 16 E r6 [15:0] $end
$var wire 1 F r6_enable $end
$var wire 1 G r6_select $end
$var wire 16 H r7 [15:0] $end
$var wire 1 I r7_enable $end
$var wire 1 J r7_select $end
$var wire 1 K r_enable $end
$var wire 1 L r_select $end
$var wire 1 M resetn $end
$var wire 16 N saida [15:0] $end
$var reg 9 O in [8:0] $end
$var reg 16 P outputProcessor [15:0] $end
$scope module comp $end
$var wire 1 0 enable $end
$var wire 16 Q iin [15:0] $end
$var reg 16 R out [15:0] $end
$upscope $end
$scope module ext $end
$var wire 16 S iin [15:0] $end
$var reg 10 T imediate [9:0] $end
$var reg 16 U out [15:0] $end
$upscope $end
$scope module count $end
$var wire 1 M clear $end
$var wire 1 * clock $end
$var reg 2 V out [1:0] $end
$upscope $end
$scope module ctrl $end
$var wire 2 W count [1:0] $end
$var wire 9 X in [8:0] $end
$var wire 8 Y outEnableRegister [7:0] $end
$var wire 8 Z outRegistera [7:0] $end
$var wire 8 [ outRegisterb [7:0] $end
$var wire 1 M resetn $end
$var reg 1 \ a_enable $end
$var reg 1 ] clear $end
$var reg 1 ^ immediate_select $end
$var reg 1 _ negar $end
$var reg 1 ` negativo $end
$var reg 1 a opSelect $end
$var reg 3 b operation [2:0] $end
$var reg 1 c r0_enable $end
$var reg 1 d r0_select $end
$var reg 1 e r1_enable $end
$var reg 1 f r1_select $end
$var reg 1 g r2_enable $end
$var reg 1 h r2_select $end
$var reg 1 i r3_enable $end
$var reg 1 j r3_select $end
$var reg 1 k r4_enable $end
$var reg 1 l r4_select $end
$var reg 1 m r5_enable $end
$var reg 1 n r5_select $end
$var reg 1 o r6_enable $end
$var reg 1 p r6_select $end
$var reg 1 q r7_enable $end
$var reg 1 r r7_select $end
$var reg 1 s r_enable $end
$var reg 1 t r_select $end
$var reg 3 u registera [2:0] $end
$var reg 3 v registerb [2:0] $end
$var reg 1 w saida $end
$var reg 2 x status [1:0] $end
$scope module dec_1 $end
$var wire 3 y register [2:0] $end
$var reg 8 z out [7:0] $end
$upscope $end
$scope module dec_2 $end
$var wire 3 { register [2:0] $end
$var reg 8 | out [7:0] $end
$upscope $end
$scope module dec_3 $end
$var wire 3 } register [2:0] $end
$var reg 8 ~ out [7:0] $end
$upscope $end
$upscope $end
$scope module mux $end
$var wire 16 !" imediate [15:0] $end
$var wire 1 . imediate_select $end
$var wire 16 "" r [15:0] $end
$var wire 16 #" r0 [15:0] $end
$var wire 1 5 r0_select $end
$var wire 16 $" r1 [15:0] $end
$var wire 1 8 r1_select $end
$var wire 16 %" r2 [15:0] $end
$var wire 1 ; r2_select $end
$var wire 16 &" r3 [15:0] $end
$var wire 1 > r3_select $end
$var wire 16 '" r4 [15:0] $end
$var wire 1 A r4_select $end
$var wire 16 (" r5 [15:0] $end
$var wire 1 D r5_select $end
$var wire 16 )" r6 [15:0] $end
$var wire 1 G r6_select $end
$var wire 16 *" r7 [15:0] $end
$var wire 1 J r7_select $end
$var wire 1 L r_select $end
$var reg 16 +" bus [15:0] $end
$upscope $end
$scope module alu $end
$var wire 1 % OpSelect $end
$var wire 16 ," a [15:0] $end
$var wire 16 -" b [15:0] $end
$var reg 16 ." result [15:0] $end
$upscope $end
$scope module R0 $end
$var wire 1 * clock $end
$var wire 1 4 enable $end
$var wire 16 /" in [15:0] $end
$var reg 16 0" out [15:0] $end
$upscope $end
$scope module R1 $end
$var wire 1 * clock $end
$var wire 1 7 enable $end
$var wire 16 1" in [15:0] $end
$var reg 16 2" out [15:0] $end
$upscope $end
$scope module R2 $end
$var wire 1 * clock $end
$var wire 1 : enable $end
$var wire 16 3" in [15:0] $end
$var reg 16 4" out [15:0] $end
$upscope $end
$scope module R3 $end
$var wire 1 * clock $end
$var wire 1 = enable $end
$var wire 16 5" in [15:0] $end
$var reg 16 6" out [15:0] $end
$upscope $end
$scope module R4 $end
$var wire 1 * clock $end
$var wire 1 @ enable $end
$var wire 16 7" in [15:0] $end
$var reg 16 8" out [15:0] $end
$upscope $end
$scope module R5 $end
$var wire 1 * clock $end
$var wire 1 C enable $end
$var wire 16 9" in [15:0] $end
$var reg 16 :" out [15:0] $end
$upscope $end
$scope module R6 $end
$var wire 1 * clock $end
$var wire 1 F enable $end
$var wire 16 ;" in [15:0] $end
$var reg 16 <" out [15:0] $end
$upscope $end
$scope module R7 $end
$var wire 1 * clock $end
$var wire 1 I enable $end
$var wire 16 =" in [15:0] $end
$var reg 16 >" out [15:0] $end
$upscope $end
$scope module Rr $end
$var wire 1 * clock $end
$var wire 1 K enable $end
$var wire 16 ?" in [15:0] $end
$var reg 16 @" out [15:0] $end
$upscope $end
$scope module Ra $end
$var wire 1 * clock $end
$var wire 1 ' enable $end
$var wire 16 A" in [15:0] $end
$var reg 16 B" out [15:0] $end
$upscope $end
$upscope $end
$upscope $end
$enddefinitions $end
#0
$dumpvars
bx B"
b0 A"
bx @"
b0 ?"
bx >"
b0 ="
bx <"
b0 ;"
bx :"
b0 9"
bx 8"
b0 7"
bx 6"
b0 5"
bx 4"
b0 3"
bx 2"
b0 1"
bx 0"
b0 /"
bx ."
b0 -"
bx ,"
b0 +"
bx *"
bx )"
bx ("
bx '"
bx &"
bx %"
bx $"
bx #"
bx ""
b0 !"
b10000000 ~
b0 }
b10000000 |
b0 {
b10000000 z
b0 y
b0 x
0w
b0 v
b0 u
0t
xs
xr
0q
xp
0o
xn
0m
xl
0k
xj
0i
xh
0g
xf
0e
xd
0c
b0 b
1a
x`
0_
x^
0]
x\
b10000000 [
b10000000 Z
b10000000 Y
b0 X
b0 W
b0 V
b0 U
b0 T
b0 S
b0 R
b0 Q
b0 P
b0 O
b0 N
0M
0L
xK
xJ
0I
bx H
xG
0F
bx E
xD
0C
bx B
xA
0@
bx ?
x>
0=
bx <
x;
0:
bx 9
x8
07
bx 6
x5
04
bx 3
bx 2
bx 1
x0
x/
z.
b0 -
b0 ,
b0 +
0*
0)
b0 (
x'
bx &
1%
0$
b0 #
0"
b0 !
$end
#1
bx P
bx !
bx R
bx (
bx -"
bx /"
bx 1"
bx 3"
bx 5"
bx 7"
bx 9"
bx ;"
bx ="
bx ?"
bx A"
bx +"
bx N
bx Q
0r
0J
0p
0G
0n
0D
0l
0A
0j
0>
0h
0;
0f
08
1d
15
0^
0/
1\
1'
b1 V
b1 +
b1 W
1"
1*
#2
0"
0*
#3
1s
1K
0\
0'
b10 V
b10 +
b10 W
1"
1*
#4
0"
0*
#5
1t
1L
0s
0K
0`
00
1c
14
bx x
b11 V
b11 +
b11 W
1"
1*
#6
0"
0*
#7
b0 x
0c
04
0t
0L
b0 V
b0 +
b0 W
1"
1*
#8
b11 x
b101 b
b11100 U
b11100 -
b11100 !"
b101000000 O
b101000000 X
b11100 T
0"
0*
b1010000000011100 #
b1010000000011100 ,
b1010000000011100 S
#9
b0 P
b0 !
b0 R
b0 (
b0 -"
b0 /"
b0 1"
b0 3"
b0 5"
b0 7"
b0 9"
b0 ;"
b0 ="
b0 ?"
b0 A"
b0 +"
b0 N
b0 Q
0d
05
1\
1'
b1 V
b1 +
b1 W
1"
1*
#10
0"
0*
#11
b0 ."
b0 1
1^
1/
1s
1K
0\
0'
b0 B"
b0 &
b0 ,"
b10 V
b10 +
b10 W
1"
1*
#12
0"
0*
#13
1t
1L
0^
0/
0s
0K
b0 @"
b0 2
b0 ""
1c
14
bx x
b11 V
b11 +
b11 W
1"
1*
#14
0"
0*
#15
b11 x
0c
04
0t
0L
b0 0"
b0 3
b0 #"
b0 V
b0 +
b0 W
1"
1*
#16
b1000000 z
b1000000 Z
b1000000 ~
b1000000 Y
b1 u
b1 y
b1 }
b101001000 O
b101001000 X
b1010 U
b1010 -
b1010 !"
b1010 T
0"
0*
b1010010000001010 #
b1010010000001010 ,
b1010010000001010 S
#17
1\
1'
b1 V
b1 +
b1 W
1"
1*
#18
0"
0*
#19
1^
1/
1s
1K
0\
0'
b10 V
b10 +
b10 W
1"
1*
#20
0"
0*
#21
1t
1L
0^
0/
0s
0K
1e
17
bx x
b11 V
b11 +
b11 W
1"
1*
#22
0"
0*
#23
b11 x
0e
07
0t
0L
b0 2"
b0 6
b0 $"
b0 V
b0 +
b0 W
1"
1*
#24
b1000000 |
b1000000 [
b10000000 ~
b10000000 Y
b10000000 z
b10000000 Z
1_
b0 x
b1 v
b1 {
b0 u
b0 y
b0 }
b1 b
b10000000 U
b10000000 -
b10000000 !"
b1000001 O
b1000001 X
b10000000 T
0"
0*
b10000010000000 #
b10000010000000 ,
b10000010000000 S
#25
1d
15
1\
1'
b1 V
b1 +
b1 W
1"
1*
#26
0"
0*
#27
1`
10
1f
18
0d
05
1s
1K
0\
0'
b10 V
b10 +
b10 W
1"
1*
#28
0"
0*
#29
1t
1L
0s
0K
0`
00
1c
14
bx x
b11 V
b11 +
b11 W
1"
1*
#30
0"
0*
#31
b0 x
0c
04
0t
0L
b0 V
b0 +
b0 W
1"
1*
#32
b10000000 |
b10000000 [
1w
0_
b1 x
b0 v
b0 {
b100 b
b100000000 O
b100000000 X
b0 U
b0 -
b0 !"
b0 T
0"
0*
b1000000000000000 #
b1000000000000000 ,
b1000000000000000 S
#33
0f
08
1\
1'
b1 V
b1 +
b1 W
1"
1*
#34
0"
0*
#35
1d
15
1s
1K
0\
0'
b10 V
b10 +
b10 W
1"
1*
#36
0"
0*
#37
1t
1L
0s
0K
1c
14
bx x
b11 V
b11 +
b11 W
1"
1*
#38
0"
0*
#39
b1 x
0c
04
0t
0L
b0 V
b0 +
b0 W
1"
1*
